leonardo_admin_honeypot
